{ "node": "Patient with PROSTATITIS", "content": "Start with a diagnosis of prostatitis", "children": [ { "node": "History and physical examination", "content": "Perform a history and physical examination", "children": [ { "node": "Urinalysis + urine culture; Urethral culture (if + risk factors for STD)", "content": "Conduct urinalysis, urine culture, and urethral culture if there are risk factors for STD", "children": [ { "node": "Hematuria", "content": "Patient has hematuria", "children": [ { "node": "Consider: Bladder cancer; Urolithiasis", "content": "Consider the possibility of bladder cancer or urolithiasis" } ] }, { "node": "+ Urine culture or + urethral culture", "content": "Positive urine culture or positive urethral culture", "children": [ { "node": "Infection resolved with antibiotics", "content": "Infection is resolved with antibiotics", "children": [ { "node": "Consider: Acute bacterial prostatitis; Urinary tract infection", "content": "Consider the possibility of acute bacterial prostatitis or urinary tract infection" } ] }, { "node": "Recurrent or persistent infection", "content": "Infection is recurrent or persistent", "children": [ { "node": "Consider: Chronic bacterial prostatitis; Prostate abscess", "content": "Consider the possibility of chronic bacterial prostatitis or prostate abscess" } ] } ] }, { "node": "Urinalysis negative for infection and blood; Urethral culture negative", "content": "Urinalysis is negative for infection and blood; Urethral culture is negative", "children": [ { "node": "Exclude: Urethral stricture; Genital herpes; Benign prostatic hypertrophy; Neurogenic bladder; Genitourinary malignancy", "content": "Exclude urethral stricture, genital herpes, benign prostatic hypertrophy, neurogenic bladder, and genitourinary malignancy", "children": [ { "node": "Consider: Chronic pelvic pain syndrome", "content": "Consider the possibility of chronic pelvic pain syndrome" } ] } ] } ] } ] } ] }