{"node": "root", "content": "Female Patient with URINARY TRACT INFECTION", "children": [{"node": "A", "content": "Upper tract signs and symptoms Pyuria", "children": [{"node": "Urine culture", "content": "Perform urine culture", "children": [{"node": "B", "content": "Mild, acute PN", "children": [{"node": "Outpatient Therapy", "content": "Outpatient Therapy x 14 days", "children": [{"node": "Clinical response", "content": "Clinical response", "children": [{"node": "Counsel patient", "content": "Counsel patient to avoid precipitating factors"}]}, {"node": "No clinical response", "content": "No clinical response", "children": [{"node": "Reculture", "content": "Reculture, Consider urologic evaluation", "children": [{"node": "No structural abnormality found", "content": "No structural abnormality found", "children": [{"node": "Antibiotic Therapy", "content": "Antibiotic Therapy x 14 days", "children": [{"node": "Reinfection", "content": "Reinfection", "children": [{"node": "Urine culture", "content": "Urine culture", "children": [{"node": "Antibiotic Therapy", "content": "Antibiotic Therapy x 4-6 wk", "children": [{"node": "Reinfection", "content": "Reinfection", "children": [{"node": "G", "content": "Consider long-term suppression, preventive measures"}]}]}]}]}]}]}, {"node": "Structural abnormality found", "content": "Structural abnormality found", "children": [{"node": "Treat underlying cause", "content": "Treat underlying cause", "children": [{"node": "Antibiotic Therapy", "content": "Antibiotic Therapy x 4-6 wk", "children": [{"node": "Reinfection", "content": "Reinfection", "children": [{"node": "Urine culture", "content": "Urine culture", "children": [{"node": "Antibiotic Therapy", "content": "Antibiotic Therapy x 14 days", "children": [{"node": "Reinfection", "content": "Reinfection", "children": [{"node": "G", "content": "Consider long-term suppression, preventive measures"}]}]}]}]}]}]}]}]}]}]}]}, {"node": "Complicated or severe PN", "content": "Complicated or severe PN", "children": [{"node": "Hospitalize", "content": "Hospitalize, IV Antibiotics, Oral Antibiotics When Afebrile, Able to Eat and Drink (Total Therapy, 14 days)", "children": [{"node": "Clinical response", "content": "Clinical response", "children": [{"node": "Counsel patient", "content": "Counsel patient to avoid precipitating factors"}]}, {"node": "No clinical response", "content": "No clinical response", "children": [{"node": "Reculture", "content": "Reculture, Consider urologic evaluation", "children": [{"node": "No structural abnormality found", "content": "No structural abnormality found", "children": [{"node": "Antibiotic Therapy", "content": "Antibiotic Therapy x 14 days", "children": [{"node": "Reinfection", "content": "Reinfection", "children": [{"node": "Urine culture", "content": "Urine culture", "children": [{"node": "Antibiotic Therapy", "content": "Antibiotic Therapy x 4-6 wk", "children": [{"node": "Reinfection", "content": "Reinfection", "children": [{"node": "G", "content": "Consider long-term suppression, preventive measures"}]}]}]}]}]}]}, {"node": "Structural abnormality found", "content": "Structural abnormality found", "children": [{"node": "Treat underlying cause", "content": "Treat underlying cause", "children": [{"node": "Antibiotic Therapy", "content": "Antibiotic Therapy x 4-6 wk", "children": [{"node": "Reinfection", "content": "Reinfection", "children": [{"node": "Urine culture", "content": "Urine culture", "children": [{"node": "Antibiotic Therapy", "content": "Antibiotic Therapy x 14 days", "children": [{"node": "Reinfection", "content": "Reinfection", "children": [{"node": "G", "content": "Consider long-term suppression, preventive measures"}]}]}]}]}]}]}]}]}]}]}]}]}]}, {"node": "Lower tract symptoms", "content": "Lower tract symptoms Pyuria", "children": [{"node": "Exclude", "content": "Exclude: Vaginitis, Herpes genitalis", "children": [{"node": "C", "content": "Risk factors for upper tract or complicated UTI", "children": [{"node": "Treat as Upper Tract Infection", "content": "Treat as Upper Tract Infection", "children": [{"node": "Clinical response", "content": "Clinical response", "children": [{"node": "E", "content": "Counsel patient to avoid precipitating factors"}]}, {"node": "No clinical response", "content": "No clinical response", "children": [{"node": "F", "content": "Urine culture", "children": [{"node": "Positive", "content": "Positive", "children": [{"node": "Antibiotic Therapy", "content": "Antibiotic Therapy x 7-10 days", "children": [{"node": "Early reinfection", "content": "Early reinfection", "children": [{"node": "Urine culture", "content": "Urine culture", "children": [{"node": "Antibiotic Therapy", "content": "Antibiotic Therapy x 14 days", "children": [{"node": "Reinfection", "content": "Reinfection", "children": [{"node": "G", "content": "Consider long-term suppression, preventive measures"}]}, {"node": "Associated with intercourse", "content": "Associated with intercourse", "children": [{"node": "Consider: Postcoital antibiotic therapy", "content": "Consider: Postcoital antibiotic therapy"}]}]}]}]}]}]}, {"node": "Negative", "content": "Negative", "children": [{"node": "Do urine probe for Chlamydia", "content": "Do urine probe for Chlamydia", "children": [{"node": "Can Treat for Chlamydia Pending Probe Result", "content": "Can Treat for Chlamydia Pending Probe Result, Doxycycline 100 mg Twice Daily x 7 days or Azithromycin 1 g Once"}]}]}]}]}]}]}, {"node": "No risk factors for upper tract or complicated UTI", "content": "No risk factors for upper tract or complicated UTI", "children": [{"node": "D", "content": "3-day Antibiotic Therapy", "children": [{"node": "Clinical response", "content": "Clinical response", "children": [{"node": "E", "content": "Counsel patient to avoid precipitating factors"}]}, {"node": "No clinical response", "content": "No clinical response", "children": [{"node": "F", "content": "Urine culture", "children": [{"node": "Positive", "content": "Positive", "children": [{"node": "Antibiotic Therapy", "content": "Antibiotic Therapy x 7-10 days", "children": [{"node": "Early reinfection", "content": "Early reinfection", "children": [{"node": "Urine culture", "content": "Urine culture", "children": [{"node": "Antibiotic Therapy", "content": "Antibiotic Therapy x 14 days", "children": [{"node": "Reinfection", "content": "Reinfection", "children": [{"node": "G", "content": "Consider long-term suppression, preventive measures"}]}, {"node": "Associated with intercourse", "content": "Associated with intercourse", "children": [{"node": "Consider: Postcoital antibiotic therapy", "content": "Consider: Postcoital antibiotic therapy"}]}]}]}]}]}]}, {"node": "Negative", "content": "Negative", "children": [{"node": "Do urine probe for Chlamydia", "content": "Do urine probe for Chlamydia", "children": [{"node": "Can Treat for Chlamydia Pending Probe Result", "content": "Can Treat for Chlamydia Pending Probe Result, Doxycycline 100 mg Twice Daily x 7 days or Azithromycin 1 g Once"}]}]}]}]}]}]}]}]}]}