{"node": "Vaginal bleeding", "content": "Pregnant patient with vaginal bleeding", "children": [{"node": "A", "content": "History: Stabilize patient. Amount of bleeding. Determine gestational age", "children": [{"node": "B", "content": "Gestational age <20 wk", "children": [{"node": "Speculum examination", "content": "Speculum examination", "children": [{"node": "Cervical os closed", "content": "Cervical os closed", "children": [{"node": "US to determine viability", "content": "US to determine viability", "children": [{"node": "Fetal cardiac activity", "content": "Fetal cardiac activity", "children": [{"node": "C", "content": "Obstetric causes: Threatened abortion, Partial mole, Loss of twin", "children": []}]}, {"node": "No fetal cardiac activity", "content": "No fetal cardiac activity", "children": [{"node": "G", "content": "Missed abortion", "children": []}, {"node": "D", "content": "Molar pregnancy", "children": []}]}]}, {"node": "E", "content": "Gynecologic causes: Cervicitis, Vaginitis, Polyps, Cancer", "children": []}, {"node": "F", "content": "Nongynecologic causes", "children": []}]}, {"node": "Cervical os open", "content": "Cervical os open", "children": [{"node": "I", "content": "Inevitable abortion", "children": []}, {"node": "J", "content": "Incomplete abortion", "children": []}, {"node": "K", "content": "Incompetent cervix", "children": []}, {"node": "H", "content": "Ectopic pregnancy", "children": []}]}]}]}, {"node": "Gestational age >20 wk", "content": "Gestational age >20 wk", "children": [{"node": "L", "content": "US evaluation", "children": [{"node": "M", "content": "Placenta previa", "children": []}, {"node": "Normal placenta location", "content": "Normal placenta location", "children": [{"node": "Speculum examination", "content": "Speculum examination", "children": [{"node": "Cervical os closed", "content": "Cervical os closed", "children": [{"node": "Obstetric causes", "content": "Obstetric causes", "children": [{"node": "N", "content": "Abruption", "children": []}, {"node": "O", "content": "Fetal bleeding", "children": []}]}, {"node": "E", "content": "Gynecologic causes", "children": []}, {"node": "F", "content": "Nongynecologic causes", "children": []}]}, {"node": "Cervical os open", "content": "Cervical os open", "children": [{"node": "P", "content": "Preterm labor", "children": []}, {"node": "K", "content": "Incompetent cervix", "children": []}, {"node": "Q", "content": "Normal labor", "children": []}]}]}]}]}]}]}]}